nmosregistration/__init__.py
nmosregistration/aggregation.py
nmosregistration/config.py
nmosregistration/etcd_backend.py
nmosregistration/etcd_util.py
nmosregistration/garbage.py
nmosregistration/modifier.py
nmosregistration/registryaggregatorservice.py
nmosregistration/common/__init__.py
nmosregistration/common/routes.py
nmosregistration/common/schema.py
nmosregistration/v1_0/__init__.py
nmosregistration/v1_0/routes.py
nmosregistration/v1_0/schema.py
nmosregistration/v1_1/__init__.py
nmosregistration/v1_1/routes.py
nmosregistration/v1_1/schema.py
nmosregistration/v1_2/__init__.py
nmosregistration/v1_2/routes.py
nmosregistration/v1_2/schema.py
nmosregistration/v1_3/__init__.py
nmosregistration/v1_3/routes.py
nmosregistration/v1_3/schema.py
usr/bin/nmosregistration
registryaggregator-0.8.1.dist-info/LICENSE.md
registryaggregator-0.8.1.dist-info/METADATA
registryaggregator-0.8.1.dist-info/WHEEL
registryaggregator-0.8.1.dist-info/top_level.txt
registryaggregator-0.8.1.dist-info/RECORD
