Metadata-Version: 2.1
Name: registryaggregator
Version: 0.8.1
Summary: BBC implementation of an AMWA NMOS Registration API
Home-page: https://github.com/bbc/nmos-registration
Author: Peter Brightwell
Author-email: peter.brightwell@bbc.co.uk
License: Apache 2
Platform: UNKNOWN
Requires-Dist: gevent (>=1.2.2)
Requires-Dist: nmoscommon (>=0.20.0)
Requires-Dist: flask (>=0.10.1)
Requires-Dist: cysystemd
Requires-Dist: ws4py (>=0.3.4)
Requires-Dist: requests (>=0.9.3)
Requires-Dist: jsonschema
Requires-Dist: six
